devjoni/arenaprog/arenalib.py
devjoni/arenaprog/arenaprog.py
devjoni/arenaprog/cameralib.py
devjoni/arenaprog/cardstimgen.py
devjoni/arenaprog/test_stepper.py
devjoni/arenaprog/version.py
devjoni/arenaprog/arenafw/AccelStepper.cpp
devjoni/arenaprog/arenafw/AccelStepper.h
devjoni/arenaprog/arenafw/arenafw.ino
devjoni_arenaprog-0.0.11.dist-info/LICENSE
devjoni_arenaprog-0.0.11.dist-info/METADATA
devjoni_arenaprog-0.0.11.dist-info/WHEEL
devjoni_arenaprog-0.0.11.dist-info/top_level.txt
devjoni_arenaprog-0.0.11.dist-info/RECORD
